{
    "DateTime": "2025-05-24 09:22:21",
    "GPU": {
        "Device": 0,
        "name": "NVIDIA GeForce RTX 3090"
    },
    "HDResult": 0.6467897891998291,
    "Input": {
        "Density": 161396.984375,
        "Files": [
            {
                "Density": 70834.8359375,
                "Grid": {
                    "BuildTime": 0.39,
                    "CellDiagonalLength": 0.08823835104703903,
                    "GiniIndex": 0.7418869137763977,
                    "GridSize": [
                        20,
                        14,
                        17
                    ],
                    "Histogram": [
                        {
                            "count": 2,
                            "percentile": 0.0,
                            "value": 1.0
                        },
                        {
                            "count": 73,
                            "percentile": 0.166667,
                            "value": 6.0
                        },
                        {
                            "count": 119,
                            "percentile": 0.333333,
                            "value": 11.0
                        },
                        {
                            "count": 184,
                            "percentile": 0.5,
                            "value": 24.0
                        },
                        {
                            "count": 206,
                            "percentile": 0.583333,
                            "value": 34.0
                        },
                        {
                            "count": 237,
                            "percentile": 0.666667,
                            "value": 42.0
                        },
                        {
                            "count": 263,
                            "percentile": 0.75,
                            "value": 66.0
                        },
                        {
                            "count": 278,
                            "percentile": 0.791667,
                            "value": 78.0
                        },
                        {
                            "count": 292,
                            "percentile": 0.833333,
                            "value": 90.0
                        },
                        {
                            "count": 310,
                            "percentile": 0.875,
                            "value": 111.0
                        },
                        {
                            "count": 314,
                            "percentile": 0.895833,
                            "value": 132.0
                        },
                        {
                            "count": 321,
                            "percentile": 0.916667,
                            "value": 179.0
                        },
                        {
                            "count": 329,
                            "percentile": 0.9375,
                            "value": 238.0
                        },
                        {
                            "count": 332,
                            "percentile": 0.947917,
                            "value": 275.0
                        },
                        {
                            "count": 336,
                            "percentile": 0.958333,
                            "value": 339.0
                        },
                        {
                            "count": 340,
                            "percentile": 0.96875,
                            "value": 352.0
                        },
                        {
                            "count": 341,
                            "percentile": 0.973958,
                            "value": 353.0
                        },
                        {
                            "count": 343,
                            "percentile": 0.979167,
                            "value": 361.0
                        },
                        {
                            "count": 346,
                            "percentile": 0.984375,
                            "value": 374.0
                        },
                        {
                            "count": 346,
                            "percentile": 0.986979,
                            "value": 374.0
                        },
                        {
                            "count": 347,
                            "percentile": 0.989583,
                            "value": 376.0
                        },
                        {
                            "count": 348,
                            "percentile": 0.992188,
                            "value": 377.0
                        },
                        {
                            "count": 348,
                            "percentile": 0.99349,
                            "value": 377.0
                        },
                        {
                            "count": 350,
                            "percentile": 0.994792,
                            "value": 382.0
                        },
                        {
                            "count": 350,
                            "percentile": 1.0,
                            "value": 382.0
                        }
                    ],
                    "MaxPoints": 1523,
                    "MedianPointsPerCell": 28,
                    "NonEmptyCells": 383,
                    "TotalCells": 4760
                },
                "MBR": [
                    {
                        "Lower": 0.0,
                        "Upper": 1.0
                    },
                    {
                        "Lower": 0.0,
                        "Upper": 0.7179046273231506
                    },
                    {
                        "Lower": 0.0,
                        "Upper": 0.8761980533599854
                    }
                ],
                "NumPoints": 44557,
                "Path": "/local/storage/shared/HDDatasets/ModelNet40/piano/train/piano_0080.off",
                "StatsGridNumPointsPerCell": 10
            },
            {
                "Density": 240736.28125,
                "Grid": {
                    "BuildTime": 0.292,
                    "CellDiagonalLength": 0.05867808684706688,
                    "GiniIndex": 0.732629120349884,
                    "GridSize": [
                        29,
                        14,
                        15
                    ],
                    "Histogram": [
                        {
                            "count": 7,
                            "percentile": 0.0,
                            "value": 2.0
                        },
                        {
                            "count": 31,
                            "percentile": 0.166667,
                            "value": 6.0
                        },
                        {
                            "count": 73,
                            "percentile": 0.333333,
                            "value": 12.0
                        },
                        {
                            "count": 98,
                            "percentile": 0.5,
                            "value": 16.0
                        },
                        {
                            "count": 103,
                            "percentile": 0.583333,
                            "value": 19.0
                        },
                        {
                            "count": 124,
                            "percentile": 0.666667,
                            "value": 30.0
                        },
                        {
                            "count": 139,
                            "percentile": 0.75,
                            "value": 36.0
                        },
                        {
                            "count": 146,
                            "percentile": 0.791667,
                            "value": 38.0
                        },
                        {
                            "count": 148,
                            "percentile": 0.833333,
                            "value": 40.0
                        },
                        {
                            "count": 155,
                            "percentile": 0.875,
                            "value": 62.0
                        },
                        {
                            "count": 158,
                            "percentile": 0.895833,
                            "value": 64.0
                        },
                        {
                            "count": 162,
                            "percentile": 0.916667,
                            "value": 80.0
                        },
                        {
                            "count": 165,
                            "percentile": 0.9375,
                            "value": 108.0
                        },
                        {
                            "count": 167,
                            "percentile": 0.947917,
                            "value": 126.0
                        },
                        {
                            "count": 169,
                            "percentile": 0.958333,
                            "value": 147.0
                        },
                        {
                            "count": 172,
                            "percentile": 0.96875,
                            "value": 180.0
                        },
                        {
                            "count": 172,
                            "percentile": 0.973958,
                            "value": 180.0
                        },
                        {
                            "count": 173,
                            "percentile": 0.979167,
                            "value": 182.0
                        },
                        {
                            "count": 174,
                            "percentile": 0.984375,
                            "value": 196.0
                        },
                        {
                            "count": 174,
                            "percentile": 0.986979,
                            "value": 196.0
                        },
                        {
                            "count": 175,
                            "percentile": 0.989583,
                            "value": 234.0
                        },
                        {
                            "count": 175,
                            "percentile": 0.992188,
                            "value": 234.0
                        },
                        {
                            "count": 175,
                            "percentile": 0.99349,
                            "value": 234.0
                        },
                        {
                            "count": 176,
                            "percentile": 0.994792,
                            "value": 238.0
                        },
                        {
                            "count": 176,
                            "percentile": 1.0,
                            "value": 238.0
                        }
                    ],
                    "MaxPoints": 1952,
                    "MedianPointsPerCell": 30,
                    "NonEmptyCells": 244,
                    "TotalCells": 6090
                },
                "MBR": [
                    {
                        "Lower": 0.0,
                        "Upper": 1.0
                    },
                    {
                        "Lower": 0.0,
                        "Upper": 0.4744878113269806
                    },
                    {
                        "Lower": 0.0,
                        "Upper": 0.49871116876602173
                    }
                ],
                "NumPoints": 56966,
                "Path": "/local/storage/shared/HDDatasets/ModelNet40/piano/test/piano_0316.off",
                "StatsGridNumPointsPerCell": 10
            }
        ],
        "Limit": 2147483647,
        "Normalize": true,
        "NumDims": 3,
        "SerializationPrefix": "/local/storage/shared/HDDatasets/ser",
        "Translate": 0.0,
        "Type": "Float"
    },
    "Running": {
        "AutoTune": true,
        "AvgTime": 3.6504000000000003,
        "EBOnlyThreshold": 500,
        "FastBuildBVH": false,
        "MaxHit": 256,
        "NumPointsPerCell": 8,
        "RebuildBVH": false,
        "Repeats": [
            {
                "Algorithm": "Ray Tracing",
                "BVHBuildTime": 0.256,
                "BVHMemoryKB": 35,
                "ComparedPairs": 0,
                "Execution": "GPU",
                "Grid": {
                    "BuildTime": 0.297,
                    "CellDiagonalLength": 0.05430205538868904,
                    "GiniIndex": 0.7264485359191895,
                    "GridSize": [
                        32,
                        15,
                        16
                    ],
                    "MaxPoints": 1919,
                    "MedianPointsPerCell": 30,
                    "NonEmptyCells": 263,
                    "TotalCells": 7680
                },
                "HDLowerBound": 0.3774868845939636,
                "HDUpperBound": 1.5109964609146118,
                "InitRadius": 0.3774868845939636,
                "Iterations": [
                    {
                        "AccumulatedComparedPoints": 855117,
                        "AccumulatedHits": 810045,
                        "AdjustBVHTime": 0.055,
                        "CMax2": 0.14249634742736816,
                        "CoveredCells": 6.951613426208496,
                        "Iteration": 1,
                        "NumInputPoints": 44557,
                        "NumOutputPoints": 6550,
                        "RTTime": 1.769,
                        "Radius": 0.3774868845939636
                    },
                    {
                        "AccumulatedComparedPoints": 1069766,
                        "AccumulatedHits": 1393423,
                        "AdjustBVHTime": 0.044,
                        "CMax2": 0.18642744421958923,
                        "CoveredCells": 7.951613426208496,
                        "Iteration": 2,
                        "NumInputPoints": 6550,
                        "NumOutputPoints": 1025,
                        "RTTime": 0.415,
                        "Radius": 0.43178895115852356
                    },
                    {
                        "AccumulatedComparedPoints": 1660775,
                        "AccumulatedHits": 1469639,
                        "AdjustBVHTime": 0.043,
                        "CMax2": 0.2344413697719574,
                        "CoveredCells": 8.951613426208496,
                        "Iteration": 3,
                        "NumInputPoints": 1025,
                        "NumOutputPoints": 170,
                        "RTTime": 0.538,
                        "Radius": 0.4860910177230835
                    },
                    {
                        "AccumulatedComparedPoints": 1667897,
                        "AccumulatedHits": 1473904,
                        "AdjustBVHTime": 0.044,
                        "CMax2": 0.28570854663848877,
                        "CoveredCells": 9.951613426208496,
                        "Iteration": 4,
                        "NumInputPoints": 170,
                        "NumOutputPoints": 102,
                        "RTTime": 0.179,
                        "Radius": 0.540393054485321
                    },
                    {
                        "AccumulatedComparedPoints": 1673879,
                        "AccumulatedHits": 1478806,
                        "CMax2": 0.41833704710006714,
                        "CoveredCells": 11.951613426208496,
                        "Iteration": 5,
                        "NumInputPoints": 102,
                        "NumOutputPoints": 0,
                        "RTTime": 0.168,
                        "Radius": 0.6489971876144409
                    }
                ],
                "Profiling": true,
                "Repeat": 1,
                "ReportedTime": 4.471
            },
            {
                "Algorithm": "Ray Tracing",
                "BVHBuildTime": 0.188,
                "BVHMemoryKB": 35,
                "ComparedPairs": 0,
                "Execution": "GPU",
                "Grid": {
                    "BuildTime": 0.264,
                    "CellDiagonalLength": 0.05430205538868904,
                    "GiniIndex": 0.7264485359191895,
                    "GridSize": [
                        32,
                        15,
                        16
                    ],
                    "MaxPoints": 1919,
                    "MedianPointsPerCell": 30,
                    "NonEmptyCells": 263,
                    "TotalCells": 7680
                },
                "HDLowerBound": 0.3774868845939636,
                "HDUpperBound": 1.5109964609146118,
                "InitRadius": 0.3774868845939636,
                "Iterations": [
                    {
                        "AccumulatedComparedPoints": 2533118,
                        "AccumulatedHits": 2288851,
                        "AdjustBVHTime": 0.044,
                        "CMax2": 0.14249634742736816,
                        "CoveredCells": 6.951613426208496,
                        "Iteration": 1,
                        "NumInputPoints": 44557,
                        "NumOutputPoints": 6550,
                        "RTTime": 1.047,
                        "Radius": 0.3774868845939636
                    },
                    {
                        "AccumulatedComparedPoints": 2746435,
                        "AccumulatedHits": 2870490,
                        "AdjustBVHTime": 0.043,
                        "CMax2": 0.18642744421958923,
                        "CoveredCells": 7.951613426208496,
                        "Iteration": 2,
                        "NumInputPoints": 6550,
                        "NumOutputPoints": 1025,
                        "RTTime": 0.414,
                        "Radius": 0.43178895115852356
                    },
                    {
                        "AccumulatedComparedPoints": 3324251,
                        "AccumulatedHits": 2950350,
                        "AdjustBVHTime": 0.043,
                        "CMax2": 0.2344413697719574,
                        "CoveredCells": 8.951613426208496,
                        "Iteration": 3,
                        "NumInputPoints": 1025,
                        "NumOutputPoints": 170,
                        "RTTime": 0.546,
                        "Radius": 0.4860910177230835
                    },
                    {
                        "AccumulatedComparedPoints": 3331127,
                        "AccumulatedHits": 2954595,
                        "AdjustBVHTime": 0.044,
                        "CMax2": 0.28570854663848877,
                        "CoveredCells": 9.951613426208496,
                        "Iteration": 4,
                        "NumInputPoints": 170,
                        "NumOutputPoints": 102,
                        "RTTime": 0.176,
                        "Radius": 0.540393054485321
                    },
                    {
                        "AccumulatedComparedPoints": 3337207,
                        "AccumulatedHits": 2959511,
                        "CMax2": 0.41833704710006714,
                        "CoveredCells": 11.951613426208496,
                        "Iteration": 5,
                        "NumInputPoints": 102,
                        "NumOutputPoints": 0,
                        "RTTime": 0.185,
                        "Radius": 0.6489971876144409
                    }
                ],
                "Profiling": true,
                "Repeat": 2,
                "ReportedTime": 3.479
            },
            {
                "Algorithm": "Ray Tracing",
                "BVHBuildTime": 0.185,
                "BVHMemoryKB": 35,
                "ComparedPairs": 0,
                "Execution": "GPU",
                "Grid": {
                    "BuildTime": 0.254,
                    "CellDiagonalLength": 0.05430205538868904,
                    "GiniIndex": 0.7264485359191895,
                    "GridSize": [
                        32,
                        15,
                        16
                    ],
                    "MaxPoints": 1919,
                    "MedianPointsPerCell": 30,
                    "NonEmptyCells": 263,
                    "TotalCells": 7680
                },
                "HDLowerBound": 0.3774868845939636,
                "HDUpperBound": 1.5109964609146118,
                "InitRadius": 0.3774868845939636,
                "Iterations": [
                    {
                        "AccumulatedComparedPoints": 4180772,
                        "AccumulatedHits": 3769556,
                        "AdjustBVHTime": 0.042,
                        "CMax2": 0.14249634742736816,
                        "CoveredCells": 6.951613426208496,
                        "Iteration": 1,
                        "NumInputPoints": 44557,
                        "NumOutputPoints": 6550,
                        "RTTime": 1.046,
                        "Radius": 0.3774868845939636
                    },
                    {
                        "AccumulatedComparedPoints": 4395046,
                        "AccumulatedHits": 4351067,
                        "AdjustBVHTime": 0.043,
                        "CMax2": 0.18642744421958923,
                        "CoveredCells": 7.951613426208496,
                        "Iteration": 2,
                        "NumInputPoints": 6550,
                        "NumOutputPoints": 1025,
                        "RTTime": 0.416,
                        "Radius": 0.43178895115852356
                    },
                    {
                        "AccumulatedComparedPoints": 5015062,
                        "AccumulatedHits": 4430035,
                        "AdjustBVHTime": 0.044,
                        "CMax2": 0.2344413697719574,
                        "CoveredCells": 8.951613426208496,
                        "Iteration": 3,
                        "NumInputPoints": 1025,
                        "NumOutputPoints": 170,
                        "RTTime": 0.537,
                        "Radius": 0.4860910177230835
                    },
                    {
                        "AccumulatedComparedPoints": 5022190,
                        "AccumulatedHits": 4434308,
                        "AdjustBVHTime": 0.043,
                        "CMax2": 0.28570854663848877,
                        "CoveredCells": 9.951613426208496,
                        "Iteration": 4,
                        "NumInputPoints": 170,
                        "NumOutputPoints": 102,
                        "RTTime": 0.176,
                        "Radius": 0.540393054485321
                    },
                    {
                        "AccumulatedComparedPoints": 5028633,
                        "AccumulatedHits": 4439132,
                        "CMax2": 0.41833704710006714,
                        "CoveredCells": 11.951613426208496,
                        "Iteration": 5,
                        "NumInputPoints": 102,
                        "NumOutputPoints": 0,
                        "RTTime": 0.16,
                        "Radius": 0.6489971876144409
                    }
                ],
                "Profiling": true,
                "Repeat": 3,
                "ReportedTime": 3.421
            },
            {
                "Algorithm": "Ray Tracing",
                "BVHBuildTime": 0.181,
                "BVHMemoryKB": 35,
                "ComparedPairs": 0,
                "Execution": "GPU",
                "Grid": {
                    "BuildTime": 0.253,
                    "CellDiagonalLength": 0.05430205538868904,
                    "GiniIndex": 0.7264485359191895,
                    "GridSize": [
                        32,
                        15,
                        16
                    ],
                    "MaxPoints": 1919,
                    "MedianPointsPerCell": 30,
                    "NonEmptyCells": 263,
                    "TotalCells": 7680
                },
                "HDLowerBound": 0.3774868845939636,
                "HDUpperBound": 1.5109964609146118,
                "InitRadius": 0.3774868845939636,
                "Iterations": [
                    {
                        "AccumulatedComparedPoints": 5886790,
                        "AccumulatedHits": 5249177,
                        "AdjustBVHTime": 0.044,
                        "CMax2": 0.14249634742736816,
                        "CoveredCells": 6.951613426208496,
                        "Iteration": 1,
                        "NumInputPoints": 44557,
                        "NumOutputPoints": 6550,
                        "RTTime": 1.048,
                        "Radius": 0.3774868845939636
                    },
                    {
                        "AccumulatedComparedPoints": 6097908,
                        "AccumulatedHits": 5831285,
                        "AdjustBVHTime": 0.042,
                        "CMax2": 0.18642744421958923,
                        "CoveredCells": 7.951613426208496,
                        "Iteration": 2,
                        "NumInputPoints": 6550,
                        "NumOutputPoints": 1025,
                        "RTTime": 0.414,
                        "Radius": 0.43178895115852356
                    },
                    {
                        "AccumulatedComparedPoints": 6695574,
                        "AccumulatedHits": 5908584,
                        "AdjustBVHTime": 0.043,
                        "CMax2": 0.2344413697719574,
                        "CoveredCells": 8.951613426208496,
                        "Iteration": 3,
                        "NumInputPoints": 1025,
                        "NumOutputPoints": 170,
                        "RTTime": 0.53,
                        "Radius": 0.4860910177230835
                    },
                    {
                        "AccumulatedComparedPoints": 6702778,
                        "AccumulatedHits": 5912869,
                        "AdjustBVHTime": 0.043,
                        "CMax2": 0.28570854663848877,
                        "CoveredCells": 9.951613426208496,
                        "Iteration": 4,
                        "NumInputPoints": 170,
                        "NumOutputPoints": 102,
                        "RTTime": 0.179,
                        "Radius": 0.540393054485321
                    },
                    {
                        "AccumulatedComparedPoints": 6710038,
                        "AccumulatedHits": 5917816,
                        "CMax2": 0.41833704710006714,
                        "CoveredCells": 11.951613426208496,
                        "Iteration": 5,
                        "NumInputPoints": 102,
                        "NumOutputPoints": 0,
                        "RTTime": 0.18,
                        "Radius": 0.6489971876144409
                    }
                ],
                "Profiling": true,
                "Repeat": 4,
                "ReportedTime": 3.422
            },
            {
                "Algorithm": "Ray Tracing",
                "BVHBuildTime": 0.186,
                "BVHMemoryKB": 35,
                "ComparedPairs": 0,
                "Execution": "GPU",
                "Grid": {
                    "BuildTime": 0.259,
                    "CellDiagonalLength": 0.05430205538868904,
                    "GiniIndex": 0.7264485359191895,
                    "GridSize": [
                        32,
                        15,
                        16
                    ],
                    "MaxPoints": 1919,
                    "MedianPointsPerCell": 30,
                    "NonEmptyCells": 263,
                    "TotalCells": 7680
                },
                "HDLowerBound": 0.3774868845939636,
                "HDUpperBound": 1.5109964609146118,
                "InitRadius": 0.3774868845939636,
                "Iterations": [
                    {
                        "AccumulatedComparedPoints": 7554716,
                        "AccumulatedHits": 6727861,
                        "AdjustBVHTime": 0.043,
                        "CMax2": 0.14249634742736816,
                        "CoveredCells": 6.951613426208496,
                        "Iteration": 1,
                        "NumInputPoints": 44557,
                        "NumOutputPoints": 6550,
                        "RTTime": 1.047,
                        "Radius": 0.3774868845939636
                    },
                    {
                        "AccumulatedComparedPoints": 7766804,
                        "AccumulatedHits": 7309381,
                        "AdjustBVHTime": 0.043,
                        "CMax2": 0.18642744421958923,
                        "CoveredCells": 7.951613426208496,
                        "Iteration": 2,
                        "NumInputPoints": 6550,
                        "NumOutputPoints": 1025,
                        "RTTime": 0.414,
                        "Radius": 0.43178895115852356
                    },
                    {
                        "AccumulatedComparedPoints": 8374224,
                        "AccumulatedHits": 7392246,
                        "AdjustBVHTime": 0.042,
                        "CMax2": 0.2344413697719574,
                        "CoveredCells": 8.951613426208496,
                        "Iteration": 3,
                        "NumInputPoints": 1025,
                        "NumOutputPoints": 170,
                        "RTTime": 0.521,
                        "Radius": 0.4860910177230835
                    },
                    {
                        "AccumulatedComparedPoints": 8380849,
                        "AccumulatedHits": 7396487,
                        "AdjustBVHTime": 0.042,
                        "CMax2": 0.28570854663848877,
                        "CoveredCells": 9.951613426208496,
                        "Iteration": 4,
                        "NumInputPoints": 170,
                        "NumOutputPoints": 102,
                        "RTTime": 0.186,
                        "Radius": 0.540393054485321
                    },
                    {
                        "AccumulatedComparedPoints": 8388551,
                        "AccumulatedHits": 7401636,
                        "CMax2": 0.41833704710006714,
                        "CoveredCells": 11.951613426208496,
                        "Iteration": 5,
                        "NumInputPoints": 102,
                        "NumOutputPoints": 0,
                        "RTTime": 0.194,
                        "Radius": 0.6489971876144409
                    }
                ],
                "Profiling": true,
                "Repeat": 5,
                "ReportedTime": 3.459
            }
        ],
        "SampleRate": 0.009999999776482582,
        "Seed": 0
    }
}