{
    "DateTime": "2025-05-22 10:52:11",
    "GPU": {
        "Device": 0,
        "l2CacheSize": 6291456,
        "maxBlocksPerMultiProcessor": 16,
        "maxThreadsPerBlock": 1024,
        "multiProcessorCount": 82,
        "name": "NVIDIA GeForce RTX 3090",
        "regsPerBlock": 65536,
        "regsPerMultiprocessor": 65536
    },
    "HDResult": 91.30169677734375,
    "Input": {
        "Density": 0.4575015902519226,
        "FileA": {
            "Density": 0.4251585602760315,
            "Grid": {
                "BuildTime": 1.988,
                "CellDiagonalLength": 4.9217143058776855,
                "GiniIndex": 0.16334596276283264,
                "GridSize": [
                    48,
                    55,
                    49
                ],
                "Histogram": [
                    {
                        "count": 523,
                        "percentile": 0.0,
                        "value": 1.0
                    },
                    {
                        "count": 10544,
                        "percentile": 0.166667,
                        "value": 17.0
                    },
                    {
                        "count": 27194,
                        "percentile": 0.333333,
                        "value": 18.0
                    },
                    {
                        "count": 31320,
                        "percentile": 0.5,
                        "value": 26.0
                    },
                    {
                        "count": 59246,
                        "percentile": 0.583333,
                        "value": 27.0
                    },
                    {
                        "count": 59246,
                        "percentile": 1.0,
                        "value": 27.0
                    }
                ],
                "MaxPoints": 27,
                "MedianPointsPerCell": 26,
                "NonEmptyCells": 59246,
                "TotalCells": 129360
            },
            "MBR": [
                {
                    "Lower": 49.0,
                    "Upper": 185.0
                },
                {
                    "Lower": 58.0,
                    "Upper": 215.0
                },
                {
                    "Lower": 0.0,
                    "Upper": 139.0
                }
            ],
            "NumPoints": 1261840,
            "Path": "/local/storage/shared/HDDatasets/BraTS2020_TrainingData/MICCAI_BraTS2020_TrainingData/BraTS20_Training_231/BraTS20_Training_231_flair.nii",
            "StatsGridNumPointsPerCell": 10
        },
        "FileB": {
            "Density": 0.3073160946369171,
            "Grid": {
                "BuildTime": 0.59,
                "CellDiagonalLength": 5.311059951782227,
                "GiniIndex": 0.1785016655921936,
                "GridSize": [
                    21,
                    29,
                    21
                ],
                "Histogram": [
                    {
                        "count": 102,
                        "percentile": 0.0,
                        "value": 1.0
                    },
                    {
                        "count": 814,
                        "percentile": 0.166667,
                        "value": 13.0
                    },
                    {
                        "count": 4487,
                        "percentile": 0.333333,
                        "value": 27.0
                    },
                    {
                        "count": 4487,
                        "percentile": 0.5,
                        "value": 27.0
                    },
                    {
                        "count": 4487,
                        "percentile": 0.583333,
                        "value": 27.0
                    },
                    {
                        "count": 4487,
                        "percentile": 0.666667,
                        "value": 27.0
                    },
                    {
                        "count": 4487,
                        "percentile": 0.75,
                        "value": 27.0
                    },
                    {
                        "count": 4487,
                        "percentile": 0.791667,
                        "value": 27.0
                    },
                    {
                        "count": 4487,
                        "percentile": 0.833333,
                        "value": 27.0
                    },
                    {
                        "count": 4487,
                        "percentile": 0.875,
                        "value": 27.0
                    },
                    {
                        "count": 4487,
                        "percentile": 0.895833,
                        "value": 27.0
                    },
                    {
                        "count": 4487,
                        "percentile": 0.916667,
                        "value": 27.0
                    },
                    {
                        "count": 4880,
                        "percentile": 0.9375,
                        "value": 36.0
                    },
                    {
                        "count": 4880,
                        "percentile": 1.0,
                        "value": 36.0
                    }
                ],
                "MaxPoints": 36,
                "MedianPointsPerCell": 27,
                "NonEmptyCells": 4880,
                "TotalCells": 12789
            },
            "MBR": [
                {
                    "Lower": 103.0,
                    "Upper": 167.0
                },
                {
                    "Lower": 56.0,
                    "Upper": 146.0
                },
                {
                    "Lower": 58.0,
                    "Upper": 122.0
                }
            ],
            "NumPoints": 113289,
            "Path": "/local/storage/shared/HDDatasets/BraTS2020_TrainingData/MICCAI_BraTS2020_TrainingData/BraTS20_Training_285/BraTS20_Training_285_seg.nii",
            "StatsGridNumPointsPerCell": 10
        },
        "Limit": 2147483647,
        "Normalize": false,
        "NumDims": 3,
        "SerializationPrefix": "/local/storage/shared/HDDatasets/ser",
        "Translate": 0.0,
        "Type": "Float"
    },
    "Running": {
        "AvgTime": 28.470399999999994,
        "FastBuildBVH": false,
        "NumPointsPerCell": 8,
        "RebuildBVH": false,
        "Repeat0": {
            "Algorithm": "Ray Tracing",
            "BVHBuildTime": 0.387,
            "BVHMemoryKB": 652,
            "ComparedPairs": 0,
            "Execution": "GPU",
            "FastBuildBVH": false,
            "Grid": {
                "BuildTime": 0.6,
                "CellDiagonalLength": 5.035309314727783,
                "GiniIndex": 0.20410601794719696,
                "GridSize": [
                    22,
                    31,
                    22
                ],
                "MaxPoints": 27,
                "MedianPointsPerCell": 27,
                "NonEmptyCells": 5488,
                "TotalCells": 15004
            },
            "HDLowerBound": 69.0,
            "HDUpperBound": 232.57041931152344,
            "InitRadius": 69.0,
            "Iter1": {
                "AccumulatedComparedPoints": 2604760,
                "AccumulatedHits": 105441192,
                "AdjustBVHTime": 0.079,
                "CMax2": 4761.0,
                "CoveredCells": 13.703229904174805,
                "NumInputPoints": 1261840,
                "NumOutputPoints": 109447,
                "RTTime": 10.935,
                "Radius": 69.0
            },
            "Iter2": {
                "AccumulatedComparedPoints": 2982029,
                "AccumulatedHits": 179116852,
                "AdjustBVHTime": 0.065,
                "CMax2": 5481.0,
                "CoveredCells": 14.703229904174805,
                "NumInputPoints": 109447,
                "NumOutputPoints": 62195,
                "RTTime": 4.546,
                "Radius": 74.03530883789063
            },
            "Iter3": {
                "AccumulatedComparedPoints": 3994360,
                "AccumulatedHits": 226137669,
                "AdjustBVHTime": 0.059,
                "CMax2": 7073.0,
                "CoveredCells": 16.703229904174805,
                "NumInputPoints": 62195,
                "NumOutputPoints": 7405,
                "RTTime": 4.273,
                "Radius": 84.10592651367188
            },
            "Iter4": {
                "AccumulatedComparedPoints": 4194627,
                "AccumulatedHits": 240648105,
                "AdjustBVHTime": 0.059,
                "CMax2": 7946.0,
                "CoveredCells": 17.703229904174805,
                "NumInputPoints": 7405,
                "NumOutputPoints": 305,
                "RTTime": 3.979,
                "Radius": 89.1412353515625
            },
            "Iter5": {
                "AccumulatedComparedPoints": 4204340,
                "AccumulatedHits": 241216377,
                "CMax2": 8336.0,
                "CoveredCells": 18.703229904174805,
                "NumInputPoints": 305,
                "NumOutputPoints": 0,
                "RTTime": 3.322,
                "Radius": 94.17654418945313
            },
            "NumPointsPerCell": 8,
            "Profiling": true,
            "RebuildBVH": false,
            "ReportedTime": 29.418,
            "SampleRate": 0.0010000000474974513,
            "Seed": 0
        },
        "Repeat1": {
            "Algorithm": "Ray Tracing",
            "BVHBuildTime": 0.271,
            "BVHMemoryKB": 652,
            "ComparedPairs": 0,
            "Execution": "GPU",
            "FastBuildBVH": false,
            "Grid": {
                "BuildTime": 0.574,
                "CellDiagonalLength": 5.035309314727783,
                "GiniIndex": 0.20410601794719696,
                "GridSize": [
                    22,
                    31,
                    22
                ],
                "MaxPoints": 27,
                "MedianPointsPerCell": 27,
                "NonEmptyCells": 5488,
                "TotalCells": 15004
            },
            "HDLowerBound": 69.0,
            "HDUpperBound": 232.57041931152344,
            "InitRadius": 69.0,
            "Iter1": {
                "AccumulatedComparedPoints": 6831148,
                "AccumulatedHits": 346657569,
                "AdjustBVHTime": 0.061,
                "CMax2": 4761.0,
                "CoveredCells": 13.703229904174805,
                "NumInputPoints": 1261840,
                "NumOutputPoints": 109447,
                "RTTime": 10.222,
                "Radius": 69.0
            },
            "Iter2": {
                "AccumulatedComparedPoints": 7205993,
                "AccumulatedHits": 420395090,
                "AdjustBVHTime": 0.06,
                "CMax2": 5481.0,
                "CoveredCells": 14.703229904174805,
                "NumInputPoints": 109447,
                "NumOutputPoints": 62195,
                "RTTime": 4.696,
                "Radius": 74.03530883789063
            },
            "Iter3": {
                "AccumulatedComparedPoints": 8201293,
                "AccumulatedHits": 466302356,
                "AdjustBVHTime": 0.059,
                "CMax2": 7073.0,
                "CoveredCells": 16.703229904174805,
                "NumInputPoints": 62195,
                "NumOutputPoints": 7405,
                "RTTime": 4.035,
                "Radius": 84.10592651367188
            },
            "Iter4": {
                "AccumulatedComparedPoints": 8401401,
                "AccumulatedHits": 480815508,
                "AdjustBVHTime": 0.058,
                "CMax2": 7946.0,
                "CoveredCells": 17.703229904174805,
                "NumInputPoints": 7405,
                "NumOutputPoints": 305,
                "RTTime": 3.896,
                "Radius": 89.1412353515625
            },
            "Iter5": {
                "AccumulatedComparedPoints": 8411114,
                "AccumulatedHits": 481383780,
                "CMax2": 8336.0,
                "CoveredCells": 18.703229904174805,
                "NumInputPoints": 305,
                "NumOutputPoints": 0,
                "RTTime": 3.448,
                "Radius": 94.17654418945313
            },
            "NumPointsPerCell": 8,
            "Profiling": true,
            "RebuildBVH": false,
            "ReportedTime": 28.304,
            "SampleRate": 0.0010000000474974513,
            "Seed": 0
        },
        "Repeat2": {
            "Algorithm": "Ray Tracing",
            "BVHBuildTime": 0.267,
            "BVHMemoryKB": 652,
            "ComparedPairs": 0,
            "Execution": "GPU",
            "FastBuildBVH": false,
            "Grid": {
                "BuildTime": 0.56,
                "CellDiagonalLength": 5.035309314727783,
                "GiniIndex": 0.20410601794719696,
                "GridSize": [
                    22,
                    31,
                    22
                ],
                "MaxPoints": 27,
                "MedianPointsPerCell": 27,
                "NonEmptyCells": 5488,
                "TotalCells": 15004
            },
            "HDLowerBound": 69.0,
            "HDUpperBound": 232.57041931152344,
            "InitRadius": 69.0,
            "Iter1": {
                "AccumulatedComparedPoints": 10901219,
                "AccumulatedHits": 586824972,
                "AdjustBVHTime": 0.06,
                "CMax2": 4761.0,
                "CoveredCells": 13.703229904174805,
                "NumInputPoints": 1261840,
                "NumOutputPoints": 109447,
                "RTTime": 10.212,
                "Radius": 69.0
            },
            "Iter2": {
                "AccumulatedComparedPoints": 11273871,
                "AccumulatedHits": 660151076,
                "AdjustBVHTime": 0.066,
                "CMax2": 5481.0,
                "CoveredCells": 14.703229904174805,
                "NumInputPoints": 109447,
                "NumOutputPoints": 62195,
                "RTTime": 4.519,
                "Radius": 74.03530883789063
            },
            "Iter3": {
                "AccumulatedComparedPoints": 12230878,
                "AccumulatedHits": 706651585,
                "AdjustBVHTime": 0.06,
                "CMax2": 7073.0,
                "CoveredCells": 16.703229904174805,
                "NumInputPoints": 62195,
                "NumOutputPoints": 7405,
                "RTTime": 4.134,
                "Radius": 84.10592651367188
            },
            "Iter4": {
                "AccumulatedComparedPoints": 12424192,
                "AccumulatedHits": 720255261,
                "AdjustBVHTime": 0.059,
                "CMax2": 7946.0,
                "CoveredCells": 17.703229904174805,
                "NumInputPoints": 7405,
                "NumOutputPoints": 305,
                "RTTime": 3.839,
                "Radius": 89.1412353515625
            },
            "Iter5": {
                "AccumulatedComparedPoints": 12433905,
                "AccumulatedHits": 720823533,
                "CMax2": 8336.0,
                "CoveredCells": 18.703229904174805,
                "NumInputPoints": 305,
                "NumOutputPoints": 0,
                "RTTime": 3.405,
                "Radius": 94.17654418945313
            },
            "NumPointsPerCell": 8,
            "Profiling": true,
            "RebuildBVH": false,
            "ReportedTime": 28.091,
            "SampleRate": 0.0010000000474974513,
            "Seed": 0
        },
        "Repeat3": {
            "Algorithm": "Ray Tracing",
            "BVHBuildTime": 0.292,
            "BVHMemoryKB": 652,
            "ComparedPairs": 0,
            "Execution": "GPU",
            "FastBuildBVH": false,
            "Grid": {
                "BuildTime": 0.557,
                "CellDiagonalLength": 5.035309314727783,
                "GiniIndex": 0.20410601794719696,
                "GridSize": [
                    22,
                    31,
                    22
                ],
                "MaxPoints": 27,
                "MedianPointsPerCell": 27,
                "NonEmptyCells": 5488,
                "TotalCells": 15004
            },
            "HDLowerBound": 69.0,
            "HDUpperBound": 232.57041931152344,
            "InitRadius": 69.0,
            "Iter1": {
                "AccumulatedComparedPoints": 15096850,
                "AccumulatedHits": 826264725,
                "AdjustBVHTime": 0.061,
                "CMax2": 4761.0,
                "CoveredCells": 13.703229904174805,
                "NumInputPoints": 1261840,
                "NumOutputPoints": 109447,
                "RTTime": 10.244,
                "Radius": 69.0
            },
            "Iter2": {
                "AccumulatedComparedPoints": 15477420,
                "AccumulatedHits": 900013362,
                "AdjustBVHTime": 0.061,
                "CMax2": 5481.0,
                "CoveredCells": 14.703229904174805,
                "NumInputPoints": 109447,
                "NumOutputPoints": 62195,
                "RTTime": 4.479,
                "Radius": 74.03530883789063
            },
            "Iter3": {
                "AccumulatedComparedPoints": 16434566,
                "AccumulatedHits": 947243194,
                "AdjustBVHTime": 0.061,
                "CMax2": 7073.0,
                "CoveredCells": 16.703229904174805,
                "NumInputPoints": 62195,
                "NumOutputPoints": 7405,
                "RTTime": 4.322,
                "Radius": 84.10592651367188
            },
            "Iter4": {
                "AccumulatedComparedPoints": 16629146,
                "AccumulatedHits": 960910076,
                "AdjustBVHTime": 0.061,
                "CMax2": 7946.0,
                "CoveredCells": 17.703229904174805,
                "NumInputPoints": 7405,
                "NumOutputPoints": 305,
                "RTTime": 3.831,
                "Radius": 89.1412353515625
            },
            "Iter5": {
                "AccumulatedComparedPoints": 16638859,
                "AccumulatedHits": 961478348,
                "CMax2": 8336.0,
                "CoveredCells": 18.703229904174805,
                "NumInputPoints": 305,
                "NumOutputPoints": 0,
                "RTTime": 3.453,
                "Radius": 94.17654418945313
            },
            "NumPointsPerCell": 8,
            "Profiling": true,
            "RebuildBVH": false,
            "ReportedTime": 28.324,
            "SampleRate": 0.0010000000474974513,
            "Seed": 0
        },
        "Repeat4": {
            "Algorithm": "Ray Tracing",
            "BVHBuildTime": 0.274,
            "BVHMemoryKB": 652,
            "ComparedPairs": 0,
            "Execution": "GPU",
            "FastBuildBVH": false,
            "Grid": {
                "BuildTime": 0.561,
                "CellDiagonalLength": 5.035309314727783,
                "GiniIndex": 0.20410601794719696,
                "GridSize": [
                    22,
                    31,
                    22
                ],
                "MaxPoints": 27,
                "MedianPointsPerCell": 27,
                "NonEmptyCells": 5488,
                "TotalCells": 15004
            },
            "HDLowerBound": 69.0,
            "HDUpperBound": 232.57041931152344,
            "InitRadius": 69.0,
            "Iter1": {
                "AccumulatedComparedPoints": 19245029,
                "AccumulatedHits": 1066919540,
                "AdjustBVHTime": 0.062,
                "CMax2": 4761.0,
                "CoveredCells": 13.703229904174805,
                "NumInputPoints": 1261840,
                "NumOutputPoints": 109447,
                "RTTime": 10.263,
                "Radius": 69.0
            },
            "Iter2": {
                "AccumulatedComparedPoints": 19623255,
                "AccumulatedHits": 1140527371,
                "AdjustBVHTime": 0.063,
                "CMax2": 5481.0,
                "CoveredCells": 14.703229904174805,
                "NumInputPoints": 109447,
                "NumOutputPoints": 62195,
                "RTTime": 4.478,
                "Radius": 74.03530883789063
            },
            "Iter3": {
                "AccumulatedComparedPoints": 20726502,
                "AccumulatedHits": 1193361795,
                "AdjustBVHTime": 0.061,
                "CMax2": 7073.0,
                "CoveredCells": 16.703229904174805,
                "NumInputPoints": 62195,
                "NumOutputPoints": 7405,
                "RTTime": 4.282,
                "Radius": 84.10592651367188
            },
            "Iter4": {
                "AccumulatedComparedPoints": 20926549,
                "AccumulatedHits": 1207844673,
                "AdjustBVHTime": 0.059,
                "CMax2": 7946.0,
                "CoveredCells": 17.703229904174805,
                "NumInputPoints": 7405,
                "NumOutputPoints": 305,
                "RTTime": 4.02,
                "Radius": 89.1412353515625
            },
            "Iter5": {
                "AccumulatedComparedPoints": 20936262,
                "AccumulatedHits": 1208412945,
                "CMax2": 8336.0,
                "CoveredCells": 18.703229904174805,
                "NumInputPoints": 305,
                "NumOutputPoints": 0,
                "RTTime": 3.273,
                "Radius": 94.17654418945313
            },
            "NumPointsPerCell": 8,
            "Profiling": true,
            "RebuildBVH": false,
            "ReportedTime": 28.215,
            "SampleRate": 0.0010000000474974513,
            "Seed": 0
        },
        "SampleRate": 0.0010000000474974513,
        "Seed": 0
    }
}